runem/VERSION
runem/__init__.py
runem/__main__.py
runem/base.py
runem/blocking_print.py
runem/cli.py
runem/command_line.py
runem/config.py
runem/config_metadata.py
runem/config_parse.py
runem/config_validate.py
runem/files.py
runem/hook_manager.py
runem/informative_dict.py
runem/job.py
runem/job_execute.py
runem/job_filter.py
runem/job_runner_module_func_path.py
runem/job_runner_simple_command.py
runem/job_wrapper.py
runem/job_wrapper_python.py
runem/log.py
runem/py.typed
runem/report.py
runem/run_command.py
runem/runem.py
runem/runem_version.py
runem/schema.yml
runem/utils.py
runem/yaml_utils.py
runem/yaml_validation.py
runem/cli/initialise_options.py
runem/types/__init__.py
runem/types/common.py
runem/types/errors.py
runem/types/filters.py
runem/types/hooks.py
runem/types/options.py
runem/types/runem_config.py
runem/types/types_jobs.py
runem-0.10.0.dist-info/licenses/LICENSE
scripts/test_hooks/__init__.py
scripts/test_hooks/json_validators.py
scripts/test_hooks/py.py
scripts/test_hooks/py.typed
scripts/test_hooks/runem_hooks.py
scripts/test_hooks/yarn.py
tests/cli/test_initialise_options.py
tests/data/help_output.3.10.txt
tests/data/help_output.3.11.txt
tests/test_types/__init__.py
tests/test_types/test_public_api.py
tests/utils/dummy_data.py
tests/utils/gen_dummy_config_metadata.py
runem-0.10.0.dist-info/METADATA
runem-0.10.0.dist-info/WHEEL
runem-0.10.0.dist-info/entry_points.txt
runem-0.10.0.dist-info/top_level.txt
runem-0.10.0.dist-info/RECORD
