Metadata-Version: 2.4
Name: runem
Version: 0.10.0
Summary: Awesome runem created by lursight
Author: lursight
License: Specify your license here
Project-URL: Homepage, https://github.com/lursight/runem/
Keywords: example,runem
Classifier: Programming Language :: Python :: 3.7
Classifier: Programming Language :: Python :: 3.8
Classifier: Programming Language :: Python :: 3.9
Classifier: Programming Language :: Python :: 3.10
Classifier: Programming Language :: Python :: 3.11
Requires-Python: >=3.7
License-File: LICENSE
Requires-Dist: packaging>=22.0
Requires-Dist: PyYAML>=5.0.0
Requires-Dist: jsonschema>=4.22
Requires-Dist: rich>10.0.0
Requires-Dist: typing_extensions>3.0.0
Provides-Extra: tests
Requires-Dist: coverage==7.5; extra == "tests"
Requires-Dist: flake8-bugbear==24.2.6; extra == "tests"
Requires-Dist: flake8==7.0.0; extra == "tests"
Requires-Dist: gitchangelog==3.0.4; extra == "tests"
Requires-Dist: mkdocs==1.5.3; extra == "tests"
Requires-Dist: mypy==1.9.0; extra == "tests"
Requires-Dist: pydocstyle==6.3.0; extra == "tests"
Requires-Dist: pylint==3.3.6; extra == "tests"
Requires-Dist: pylama==8.4.1; extra == "tests"
Requires-Dist: pytest-cov==6.1.1; extra == "tests"
Requires-Dist: pytest-profiling==1.7.0; extra == "tests"
Requires-Dist: pytest-xdist==3.6.1; extra == "tests"
Requires-Dist: pytest==8.3.5; extra == "tests"
Requires-Dist: ruff==0.11.6; extra == "tests"
Requires-Dist: setuptools; extra == "tests"
Requires-Dist: termplotlib==0.3.9; extra == "tests"
Requires-Dist: tox; extra == "tests"
Requires-Dist: types-PyYAML==6.0.12.20240311; extra == "tests"
Requires-Dist: requests-mock==1.11.0; extra == "tests"
Requires-Dist: types-jsonschema; extra == "tests"
Requires-Dist: types-setuptools; extra == "tests"
Dynamic: license-file
